native_web_app.py
native_web_app-1.0.1.dist-info/LICENSE
native_web_app-1.0.1.dist-info/METADATA
native_web_app-1.0.1.dist-info/WHEEL
native_web_app-1.0.1.dist-info/top_level.txt
native_web_app-1.0.1.dist-info/RECORD
