Metadata-Version: 2.1
Name: native-web-app
Version: 1.0.1
Summary: Build Electron-like apps without Electron
Home-page: https://github.com/mhils/native_web_app
Author: Maximilian Hils
Author-email: pypi@maximilianhils.com
License: MIT
Keywords: webbrowser electron browser pwa webapp
Platform: UNKNOWN
Classifier: License :: OSI Approved :: MIT License
Classifier: Development Status :: 5 - Production/Stable
Classifier: Operating System :: OS Independent
Classifier: Topic :: Internet :: WWW/HTTP :: Browsers
Classifier: Programming Language :: Python :: 3.7
Classifier: Programming Language :: Python :: 3.8
Classifier: Programming Language :: Python :: 3.9
Classifier: Typing :: Typed
Requires-Python: >=3.7
